{
  "protocol_version" : "0.0.6",
  "configuration" : {
    "version" : "(6.13.0) (explicit/7ea6b90eb94)",
    "tlc" : "__thread",
    "sigsgev" : "normal",
    "notifications" : "kqueue",
    "architecture" : "arm64",
    "disabled_features" : "com,shared_perfcounters",
    "smallconfig" : "disabled",
    "bigarrays" : "disabled",
    "softdebug" : "enabled",
    "interpreter" : "enabled",
    "llvm_support" : "disabled",
    "suspend" : "preemptive"
  },
  "memory" : {
    "Resident Size" : "511492096",
    "Virtual Size" : "421269569536",
    "minor_gc_time" : "0",
    "major_gc_time" : "19841",
    "minor_gc_count" : "0",
    "major_gc_count" : "2",
    "major_gc_time_concurrent" : "0"
 },
  "threads" : [
 {
    "is_managed" : true,
    "offset_free_hash" : "0x2543dd1cf0",
    "offset_rich_hash" : "0x2543dd2410",
    "crashed" : true,
    "native_thread_id" : "0x108f74580",
    "thread_info_addr" : "0x13f959600",
    "thread_name" : "tid_103",
    "ctx" : {
      "IP" : "0x1426b0748",
      "SP" : "0x16ce193c0",
      "BP" : "0x16ce19400"
  },
    "managed_frames" : [
  {
      "is_managed" : "false",
      "native_address" : "unregistered"
   }
,
  {
      "is_managed" : "true",
      "guid" : "E38A6D3E-E47C-43EB-9B2E-49C63FC0AA48",
      "token" : "0x00000",
      "native_offset" : "0x0",
      "filename" : "mscorlib.dll",
      "sizeofimage" : "0x470000",
      "timestamp" : "0xaf0ada7a",
      "il_offset" : "0xffffffff"
   }
,
  {
      "is_managed" : "true",
      "guid" : "E38A6D3E-E47C-43EB-9B2E-49C63FC0AA48",
      "token" : "0x6005474",
      "native_offset" : "0x0",
      "filename" : "mscorlib.dll",
      "sizeofimage" : "0x470000",
      "timestamp" : "0xaf0ada7a",
      "il_offset" : "0x00051"
   }
,
  {
      "is_managed" : "true",
      "guid" : "E38A6D3E-E47C-43EB-9B2E-49C63FC0AA48",
      "token" : "0x6005469",
      "native_offset" : "0x0",
      "filename" : "mscorlib.dll",
      "sizeofimage" : "0x470000",
      "timestamp" : "0xaf0ada7a",
      "il_offset" : "0x0005c"
   }
,
  {
      "is_managed" : "true",
      "guid" : "E38A6D3E-E47C-43EB-9B2E-49C63FC0AA48",
      "token" : "0x6005482",
      "native_offset" : "0x0",
      "filename" : "mscorlib.dll",
      "sizeofimage" : "0x470000",
      "timestamp" : "0xaf0ada7a",
      "il_offset" : "0x00093"
   }
,
  {
      "is_managed" : "true",
      "guid" : "E38A6D3E-E47C-43EB-9B2E-49C63FC0AA48",
      "token" : "0x60057f9",
      "native_offset" : "0x0",
      "filename" : "mscorlib.dll",
      "sizeofimage" : "0x470000",
      "timestamp" : "0xaf0ada7a",
      "il_offset" : "0x00016"
   }
,
  {
      "is_managed" : "true",
      "guid" : "E38A6D3E-E47C-43EB-9B2E-49C63FC0AA48",
      "token" : "0x60057f8",
      "native_offset" : "0x0",
      "filename" : "mscorlib.dll",
      "sizeofimage" : "0x470000",
      "timestamp" : "0xaf0ada7a",
      "il_offset" : "0x00007"
   }
,
  {
      "is_managed" : "true",
      "guid" : "E38A6D3E-E47C-43EB-9B2E-49C63FC0AA48",
      "token" : "0x00000",
      "native_offset" : "0x0",
      "filename" : "mscorlib.dll",
      "sizeofimage" : "0x470000",
      "timestamp" : "0xaf0ada7a",
      "il_offset" : "0x00032"
   }
,
  {
      "is_managed" : "true",
      "guid" : "44DDE17B-B74E-4847-AC96-FA1D80D6D096",
      "token" : "0x6000dd6",
      "native_offset" : "0x0",
      "filename" : "Burst.Compiler.IL.dll",
      "sizeofimage" : "0x164000",
      "timestamp" : "0xaf1ba364",
      "il_offset" : "0x00010"
   }
,
  {
      "is_managed" : "true",
      "guid" : "44DDE17B-B74E-4847-AC96-FA1D80D6D096",
      "token" : "0x6000dd7",
      "native_offset" : "0x0",
      "filename" : "Burst.Compiler.IL.dll",
      "sizeofimage" : "0x164000",
      "timestamp" : "0xaf1ba364",
      "il_offset" : "0x00068"
   }
,
  {
      "is_managed" : "true",
      "guid" : "44DDE17B-B74E-4847-AC96-FA1D80D6D096",
      "token" : "0x6000dca",
      "native_offset" : "0x0",
      "filename" : "Burst.Compiler.IL.dll",
      "sizeofimage" : "0x164000",
      "timestamp" : "0xaf1ba364",
      "il_offset" : "0x00038"
   }
,
  {
      "is_managed" : "true",
      "guid" : "44DDE17B-B74E-4847-AC96-FA1D80D6D096",
      "token" : "0x6000023",
      "native_offset" : "0x0",
      "filename" : "Burst.Compiler.IL.dll",
      "sizeofimage" : "0x164000",
      "timestamp" : "0xaf1ba364",
      "il_offset" : "0x00063"
   }
,
  {
      "is_managed" : "true",
      "guid" : "44DDE17B-B74E-4847-AC96-FA1D80D6D096",
      "token" : "0x6000015",
      "native_offset" : "0x0",
      "filename" : "Burst.Compiler.IL.dll",
      "sizeofimage" : "0x164000",
      "timestamp" : "0xaf1ba364",
      "il_offset" : "0x00087"
   }
,
  {
      "is_managed" : "true",
      "guid" : "44DDE17B-B74E-4847-AC96-FA1D80D6D096",
      "token" : "0x6000016",
      "native_offset" : "0x0",
      "filename" : "Burst.Compiler.IL.dll",
      "sizeofimage" : "0x164000",
      "timestamp" : "0xaf1ba364",
      "il_offset" : "0x00000"
   }
,
  {
      "is_managed" : "true",
      "guid" : "44DDE17B-B74E-4847-AC96-FA1D80D6D096",
      "token" : "0x6000718",
      "native_offset" : "0x0",
      "filename" : "Burst.Compiler.IL.dll",
      "sizeofimage" : "0x164000",
      "timestamp" : "0xaf1ba364",
      "il_offset" : "0x000f3"
   }
,
  {
      "is_managed" : "true",
      "guid" : "44DDE17B-B74E-4847-AC96-FA1D80D6D096",
      "token" : "0x6000784",
      "native_offset" : "0x0",
      "filename" : "Burst.Compiler.IL.dll",
      "sizeofimage" : "0x164000",
      "timestamp" : "0xaf1ba364",
      "il_offset" : "0x0003c"
   }
,
  {
      "is_managed" : "true",
      "guid" : "44DDE17B-B74E-4847-AC96-FA1D80D6D096",
      "token" : "0x600077f",
      "native_offset" : "0x0",
      "filename" : "Burst.Compiler.IL.dll",
      "sizeofimage" : "0x164000",
      "timestamp" : "0xaf1ba364",
      "il_offset" : "0x0004a"
   }
,
  {
      "is_managed" : "true",
      "guid" : "44DDE17B-B74E-4847-AC96-FA1D80D6D096",
      "token" : "0x00000",
      "native_offset" : "0x0",
      "filename" : "Burst.Compiler.IL.dll",
      "sizeofimage" : "0x164000",
      "timestamp" : "0xaf1ba364",
      "il_offset" : "0x0002a"
   }
,
  {
      "is_managed" : "false",
      "native_address" : "unregistered"
   }
,
  {
      "is_managed" : "true",
      "guid" : "AE8040E5-4D95-43E4-8A88-885839CE8CC6",
      "token" : "0x00000",
      "native_offset" : "0x0",
      "filename" : "UnityEngine.CoreModule.dll",
      "sizeofimage" : "0x15e000",
      "timestamp" : "0xbe0db00e",
      "il_offset" : "0xffffffff"
   }
,
  {
      "is_managed" : "true",
      "guid" : "4E268A98-8E25-4462-B27E-542BC5B526E7",
      "token" : "0x6000043",
      "native_offset" : "0x0",
      "filename" : "Unity.Burst.dll",
      "sizeofimage" : "0x58000",
      "timestamp" : "0x9a3ea607",
      "il_offset" : "0x00020"
   }
,
  {
      "is_managed" : "true",
      "guid" : "4E268A98-8E25-4462-B27E-542BC5B526E7",
      "token" : "0x600002f",
      "native_offset" : "0x0",
      "filename" : "Unity.Burst.dll",
      "sizeofimage" : "0x58000",
      "timestamp" : "0x9a3ea607",
      "il_offset" : "0x00000"
   }
,
  {
      "is_managed" : "true",
      "guid" : "4E268A98-8E25-4462-B27E-542BC5B526E7",
      "token" : "0x6000154",
      "native_offset" : "0x0",
      "filename" : "Unity.Burst.dll",
      "sizeofimage" : "0x58000",
      "timestamp" : "0x9a3ea607",
      "il_offset" : "0x00138"
   }
,
  {
      "is_managed" : "true",
      "guid" : "E38A6D3E-E47C-43EB-9B2E-49C63FC0AA48",
      "token" : "0x00000",
      "native_offset" : "0x0",
      "filename" : "mscorlib.dll",
      "sizeofimage" : "0x470000",
      "timestamp" : "0xaf0ada7a",
      "il_offset" : "0x0002a"
   }
,
  {
      "is_managed" : "false",
      "native_address" : "unregistered"
   }
,
  {
      "is_managed" : "true",
      "guid" : "E38A6D3E-E47C-43EB-9B2E-49C63FC0AA48",
      "token" : "0x00000",
      "native_offset" : "0x0",
      "filename" : "mscorlib.dll",
      "sizeofimage" : "0x470000",
      "timestamp" : "0xaf0ada7a",
      "il_offset" : "0xffffffff"
   }
,
  {
      "is_managed" : "true",
      "guid" : "E38A6D3E-E47C-43EB-9B2E-49C63FC0AA48",
      "token" : "0x600471a",
      "native_offset" : "0x0",
      "filename" : "mscorlib.dll",
      "sizeofimage" : "0x470000",
      "timestamp" : "0xaf0ada7a",
      "il_offset" : "0x0002a"
   }
,
  {
      "is_managed" : "true",
      "guid" : "0ABE8B4B-FEC1-494E-BDD6-C2792482FF16",
      "token" : "0x6002b49",
      "native_offset" : "0x0",
      "filename" : "UnityEditor.CoreModule.dll",
      "sizeofimage" : "0x816000",
      "timestamp" : "0xac105300",
      "il_offset" : "0x00081"
   }
,
  {
      "is_managed" : "true",
      "guid" : "0ABE8B4B-FEC1-494E-BDD6-C2792482FF16",
      "token" : "0x00000",
      "native_offset" : "0x0",
      "filename" : "UnityEditor.CoreModule.dll",
      "sizeofimage" : "0x816000",
      "timestamp" : "0xac105300",
      "il_offset" : "0x0002a"
   }

  ],
  "unmanaged_frames" : [
 {
    "is_managed" : "false",
    "native_address" : "0x142505ec0",
    "native_offset" : "0x00000"
  }
,
 {
    "is_managed" : "false",
    "native_address" : "0x14263c8cc",
    "native_offset" : "0x00000"
  }
,
 {
    "is_managed" : "false",
    "native_address" : "0x14263cc28",
    "native_offset" : "0x00000"
  }
,
 {
    "is_managed" : "false",
    "native_address" : "0x14263d218",
    "native_offset" : "0x00000"
  }
,
 {
    "is_managed" : "false",
    "native_address" : "0x142547c14",
    "native_offset" : "0x00000"
  }
,
 {
    "is_managed" : "false",
    "native_address" : "0x142509f50",
    "native_offset" : "0x00000"
  }
,
 {
    "is_managed" : "false",
    "native_address" : "0x1424928b4",
    "native_offset" : "0x00000"
  }
,
 {
    "is_managed" : "false",
    "native_address" : "0x1c1d374a4",
    "native_offset" : "0x00000"
  }
,
 {
    "is_managed" : "false",
    "native_address" : "0x142679e50",
    "native_offset" : "0x00000"
  }
,
 {
    "is_managed" : "false",
    "native_address" : "0x1426ae9f0",
    "native_offset" : "0x00000"
  }
,
 {
    "is_managed" : "false",
    "native_address" : "0x1426adfdc",
    "native_offset" : "0x00000"
  }
,
 {
    "is_managed" : "false",
    "native_address" : "0x1426ada40",
    "native_offset" : "0x00000"
  }
,
 {
    "is_managed" : "false",
    "native_address" : "0x1426ae5fc",
    "native_offset" : "0x00000"
  }
,
 {
    "is_managed" : "false",
    "native_address" : "0x1426b4a1c",
    "native_offset" : "0x00000"
  }
,
 {
    "is_managed" : "false",
    "native_address" : "0x1426b0dc8",
    "native_offset" : "0x00000"
  }
,
 {
    "is_managed" : "false",
    "native_address" : "0x1426b4d94",
    "native_offset" : "0x00000"
  }
,
 {
    "is_managed" : "false",
    "native_address" : "0x14267a9ec",
    "native_offset" : "0x00000"
  }
,
 {
    "is_managed" : "false",
    "native_address" : "0x142620c48",
    "native_offset" : "0x00000"
  }
,
 {
    "is_managed" : "false",
    "native_address" : "0x142620d6c",
    "native_offset" : "0x00000"
  }
,
 {
    "is_managed" : "true",
    "guid" : "E38A6D3E-E47C-43EB-9B2E-49C63FC0AA48",
    "token" : "0x00000",
    "native_offset" : "0x0",
    "filename" : "mscorlib.dll",
    "sizeofimage" : "0x470000",
    "timestamp" : "0xaf0ada7a",
    "il_offset" : "0x00000"
  }
,
 {
    "is_managed" : "true",
    "guid" : "E38A6D3E-E47C-43EB-9B2E-49C63FC0AA48",
    "token" : "0x6005474",
    "native_offset" : "0x0",
    "filename" : "mscorlib.dll",
    "sizeofimage" : "0x470000",
    "timestamp" : "0xaf0ada7a",
    "il_offset" : "0x00000"
  }
,
 {
    "is_managed" : "true",
    "guid" : "E38A6D3E-E47C-43EB-9B2E-49C63FC0AA48",
    "token" : "0x6005469",
    "native_offset" : "0x0",
    "filename" : "mscorlib.dll",
    "sizeofimage" : "0x470000",
    "timestamp" : "0xaf0ada7a",
    "il_offset" : "0x00000"
  }
,
 {
    "is_managed" : "true",
    "guid" : "E38A6D3E-E47C-43EB-9B2E-49C63FC0AA48",
    "token" : "0x6005482",
    "native_offset" : "0x0",
    "filename" : "mscorlib.dll",
    "sizeofimage" : "0x470000",
    "timestamp" : "0xaf0ada7a",
    "il_offset" : "0x00000"
  }
,
 {
    "is_managed" : "true",
    "guid" : "E38A6D3E-E47C-43EB-9B2E-49C63FC0AA48",
    "token" : "0x60057f9",
    "native_offset" : "0x0",
    "filename" : "mscorlib.dll",
    "sizeofimage" : "0x470000",
    "timestamp" : "0xaf0ada7a",
    "il_offset" : "0x00000"
  }
,
 {
    "is_managed" : "true",
    "guid" : "E38A6D3E-E47C-43EB-9B2E-49C63FC0AA48",
    "token" : "0x60057f8",
    "native_offset" : "0x0",
    "filename" : "mscorlib.dll",
    "sizeofimage" : "0x470000",
    "timestamp" : "0xaf0ada7a",
    "il_offset" : "0x00000"
  }
,
 {
    "is_managed" : "true",
    "guid" : "E38A6D3E-E47C-43EB-9B2E-49C63FC0AA48",
    "token" : "0x00000",
    "native_offset" : "0x0",
    "filename" : "mscorlib.dll",
    "sizeofimage" : "0x470000",
    "timestamp" : "0xaf0ada7a",
    "il_offset" : "0x00000"
  }
,
 {
    "is_managed" : "true",
    "guid" : "44DDE17B-B74E-4847-AC96-FA1D80D6D096",
    "token" : "0x6000dd6",
    "native_offset" : "0x0",
    "filename" : "Burst.Compiler.IL.dll",
    "sizeofimage" : "0x164000",
    "timestamp" : "0xaf1ba364",
    "il_offset" : "0x00000"
  }
,
 {
    "is_managed" : "true",
    "guid" : "44DDE17B-B74E-4847-AC96-FA1D80D6D096",
    "token" : "0x6000dd7",
    "native_offset" : "0x0",
    "filename" : "Burst.Compiler.IL.dll",
    "sizeofimage" : "0x164000",
    "timestamp" : "0xaf1ba364",
    "il_offset" : "0x00000"
  }
,
 {
    "is_managed" : "true",
    "guid" : "44DDE17B-B74E-4847-AC96-FA1D80D6D096",
    "token" : "0x6000dca",
    "native_offset" : "0x0",
    "filename" : "Burst.Compiler.IL.dll",
    "sizeofimage" : "0x164000",
    "timestamp" : "0xaf1ba364",
    "il_offset" : "0x00000"
  }
,
 {
    "is_managed" : "true",
    "guid" : "44DDE17B-B74E-4847-AC96-FA1D80D6D096",
    "token" : "0x6000023",
    "native_offset" : "0x0",
    "filename" : "Burst.Compiler.IL.dll",
    "sizeofimage" : "0x164000",
    "timestamp" : "0xaf1ba364",
    "il_offset" : "0x00000"
  }
,
 {
    "is_managed" : "true",
    "guid" : "44DDE17B-B74E-4847-AC96-FA1D80D6D096",
    "token" : "0x6000015",
    "native_offset" : "0x0",
    "filename" : "Burst.Compiler.IL.dll",
    "sizeofimage" : "0x164000",
    "timestamp" : "0xaf1ba364",
    "il_offset" : "0x00000"
  }
,
 {
    "is_managed" : "true",
    "guid" : "44DDE17B-B74E-4847-AC96-FA1D80D6D096",
    "token" : "0x6000016",
    "native_offset" : "0x0",
    "filename" : "Burst.Compiler.IL.dll",
    "sizeofimage" : "0x164000",
    "timestamp" : "0xaf1ba364",
    "il_offset" : "0x00000"
  }
,
 {
    "is_managed" : "true",
    "guid" : "44DDE17B-B74E-4847-AC96-FA1D80D6D096",
    "token" : "0x6000718",
    "native_offset" : "0x0",
    "filename" : "Burst.Compiler.IL.dll",
    "sizeofimage" : "0x164000",
    "timestamp" : "0xaf1ba364",
    "il_offset" : "0x00000"
  }
,
 {
    "is_managed" : "true",
    "guid" : "44DDE17B-B74E-4847-AC96-FA1D80D6D096",
    "token" : "0x6000784",
    "native_offset" : "0x0",
    "filename" : "Burst.Compiler.IL.dll",
    "sizeofimage" : "0x164000",
    "timestamp" : "0xaf1ba364",
    "il_offset" : "0x00000"
  }
,
 {
    "is_managed" : "true",
    "guid" : "44DDE17B-B74E-4847-AC96-FA1D80D6D096",
    "token" : "0x600077f",
    "native_offset" : "0x0",
    "filename" : "Burst.Compiler.IL.dll",
    "sizeofimage" : "0x164000",
    "timestamp" : "0xaf1ba364",
    "il_offset" : "0x00000"
  }
,
 {
    "is_managed" : "true",
    "guid" : "44DDE17B-B74E-4847-AC96-FA1D80D6D096",
    "token" : "0x00000",
    "native_offset" : "0x0",
    "filename" : "Burst.Compiler.IL.dll",
    "sizeofimage" : "0x164000",
    "timestamp" : "0xaf1ba364",
    "il_offset" : "0x00000"
  }
,
 {
    "is_managed" : "false",
    "native_address" : "0x142495b74",
    "native_offset" : "0x00000"
  }
,
 {
    "is_managed" : "false",
    "native_address" : "0x14261b7ec",
    "native_offset" : "0x00000"
  }
,
 {
    "is_managed" : "false",
    "native_address" : "0x14261b70c",
    "native_offset" : "0x00000"
  }
,
 {
    "is_managed" : "false",
    "native_address" : "0x103c1f2d0",
    "native_offset" : "0x00000"
  }
,
 {
    "is_managed" : "false",
    "native_address" : "0x103c1a440",
    "native_offset" : "0x00000"
  }
,
 {
    "is_managed" : "false",
    "native_address" : "0x103588b9c",
    "native_offset" : "0x00000"
  }
,
 {
    "is_managed" : "false",
    "native_address" : "0x10358c124",
    "native_offset" : "0x00000"
  }
,
 {
    "is_managed" : "false",
    "native_address" : "0x102fe7b4c",
    "native_offset" : "0x00000"
  }
,
 {
    "is_managed" : "true",
    "guid" : "AE8040E5-4D95-43E4-8A88-885839CE8CC6",
    "token" : "0x00000",
    "native_offset" : "0x0",
    "filename" : "UnityEngine.CoreModule.dll",
    "sizeofimage" : "0x15e000",
    "timestamp" : "0xbe0db00e",
    "il_offset" : "0x00000"
  }
,
 {
    "is_managed" : "true",
    "guid" : "4E268A98-8E25-4462-B27E-542BC5B526E7",
    "token" : "0x6000043",
    "native_offset" : "0x0",
    "filename" : "Unity.Burst.dll",
    "sizeofimage" : "0x58000",
    "timestamp" : "0x9a3ea607",
    "il_offset" : "0x00000"
  }
,
 {
    "is_managed" : "true",
    "guid" : "4E268A98-8E25-4462-B27E-542BC5B526E7",
    "token" : "0x600002f",
    "native_offset" : "0x0",
    "filename" : "Unity.Burst.dll",
    "sizeofimage" : "0x58000",
    "timestamp" : "0x9a3ea607",
    "il_offset" : "0x00000"
  }
,
 {
    "is_managed" : "true",
    "guid" : "4E268A98-8E25-4462-B27E-542BC5B526E7",
    "token" : "0x6000154",
    "native_offset" : "0x0",
    "filename" : "Unity.Burst.dll",
    "sizeofimage" : "0x58000",
    "timestamp" : "0x9a3ea607",
    "il_offset" : "0x00000"
  }
,
 {
    "is_managed" : "true",
    "guid" : "E38A6D3E-E47C-43EB-9B2E-49C63FC0AA48",
    "token" : "0x00000",
    "native_offset" : "0x0",
    "filename" : "mscorlib.dll",
    "sizeofimage" : "0x470000",
    "timestamp" : "0xaf0ada7a",
    "il_offset" : "0x00000"
  }
,
 {
    "is_managed" : "false",
    "native_address" : "0x142495b74",
    "native_offset" : "0x00000"
  }
,
 {
    "is_managed" : "false",
    "native_address" : "0x14261b7ec",
    "native_offset" : "0x00000"
  }
,
 {
    "is_managed" : "false",
    "native_address" : "0x142617c24",
    "native_offset" : "0x00000"
  }
,
 {
    "is_managed" : "false",
    "native_address" : "0x1425dcba4",
    "native_offset" : "0x00000"
  }
,
 {
    "is_managed" : "true",
    "guid" : "E38A6D3E-E47C-43EB-9B2E-49C63FC0AA48",
    "token" : "0x00000",
    "native_offset" : "0x0",
    "filename" : "mscorlib.dll",
    "sizeofimage" : "0x470000",
    "timestamp" : "0xaf0ada7a",
    "il_offset" : "0x00000"
  }
,
 {
    "is_managed" : "true",
    "guid" : "E38A6D3E-E47C-43EB-9B2E-49C63FC0AA48",
    "token" : "0x600471a",
    "native_offset" : "0x0",
    "filename" : "mscorlib.dll",
    "sizeofimage" : "0x470000",
    "timestamp" : "0xaf0ada7a",
    "il_offset" : "0x00000"
  }
,
 {
    "is_managed" : "true",
    "guid" : "0ABE8B4B-FEC1-494E-BDD6-C2792482FF16",
    "token" : "0x6002b49",
    "native_offset" : "0x0",
    "filename" : "UnityEditor.CoreModule.dll",
    "sizeofimage" : "0x816000",
    "timestamp" : "0xac105300",
    "il_offset" : "0x00000"
  }
,
 {
    "is_managed" : "true",
    "guid" : "0ABE8B4B-FEC1-494E-BDD6-C2792482FF16",
    "token" : "0x00000",
    "native_offset" : "0x0",
    "filename" : "UnityEditor.CoreModule.dll",
    "sizeofimage" : "0x816000",
    "timestamp" : "0xac105300",
    "il_offset" : "0x00000"
  }
,
 {
    "is_managed" : "false",
    "native_address" : "0x142495b74",
    "native_offset" : "0x00000"
  }
,
 {
    "is_managed" : "false",
    "native_address" : "0x14261b7ec",
    "native_offset" : "0x00000"
  }
,
 {
    "is_managed" : "false",
    "native_address" : "0x14261b70c",
    "native_offset" : "0x00000"
  }
,
 {
    "is_managed" : "false",
    "native_address" : "0x103c1f2d0",
    "native_offset" : "0x00000"
  }
,
 {
    "is_managed" : "false",
    "native_address" : "0x103c1a440",
    "native_offset" : "0x00000"
  }
,
 {
    "is_managed" : "false",
    "native_address" : "0x103d29b18",
    "native_offset" : "0x00000"
  }
,
 {
    "is_managed" : "false",
    "native_address" : "0x103bcc464",
    "native_offset" : "0x00000"
  }
,
 {
    "is_managed" : "false",
    "native_address" : "0x103bce780",
    "native_offset" : "0x00000"
  }
,
 {
    "is_managed" : "false",
    "native_address" : "0x103bcca48",
    "native_offset" : "0x00000"
  }
,
 {
    "is_managed" : "false",
    "native_address" : "0x1047128d4",
    "native_offset" : "0x00000"
  }
,
 {
    "is_managed" : "false",
    "native_address" : "0x104711dd8",
    "native_offset" : "0x00000"
  }
,
 {
    "is_managed" : "false",
    "native_address" : "0x104ee4208",
    "native_offset" : "0x00000"
  }
,
 {
    "is_managed" : "false",
    "native_address" : "0x104ebe438",
    "native_offset" : "0x00000"
  }
,
 {
    "is_managed" : "false",
    "native_address" : "0x104ebfef4",
    "native_offset" : "0x00000"
  }
,
 {
    "is_managed" : "false",
    "native_address" : "0x104aa1f8c",
    "native_offset" : "0x00000"
  }
,
 {
    "is_managed" : "false",
    "native_address" : "0x10582aacc",
    "native_offset" : "0x00000"
  }
,
 {
    "is_managed" : "false",
    "native_address" : "0x1c1de151c",
    "native_offset" : "0x00000"
  }
,
 {
    "is_managed" : "false",
    "native_address" : "0x1c1e85c18",
    "native_offset" : "0x00000"
  }
,
 {
    "is_managed" : "false",
    "native_address" : "0x1c1e85b84",
    "native_offset" : "0x00000"
  }
,
 {
    "is_managed" : "false",
    "native_address" : "0x1c1db01c0",
    "native_offset" : "0x00000"
  }
,
 {
    "is_managed" : "false",
    "native_address" : "0x1c2c75c98",
    "native_offset" : "0x00000"
  }
,
 {
    "is_managed" : "false",
    "native_address" : "0x1c495b28c",
    "native_offset" : "0x00000"
  }
,
 {
    "is_managed" : "false",
    "native_address" : "0x1c495afa4",
    "native_offset" : "0x00000"
  }

 ]
}
]
}